djangoaddicts/__init__.py
djangoaddicts/codegen/__init__.py
djangoaddicts/codegen/apps.py
djangoaddicts/codegen/management/__init__.py
djangoaddicts/codegen/management/commands/__init__.py
djangoaddicts/codegen/management/commands/generate_admin.py
djangoaddicts/codegen/management/commands/generate_drf.py
djangoaddicts/codegen/management/commands/generate_unittests.py
djangoaddicts/codegen/management/commands/admin_templates/admin.jinja
djangoaddicts/codegen/management/commands/drf_templates/filterset.jinja
djangoaddicts/codegen/management/commands/drf_templates/serializer.jinja
djangoaddicts/codegen/management/commands/drf_templates/urls.jinja
djangoaddicts/codegen/management/commands/drf_templates/viewset.jinja
djangoaddicts/codegen/management/commands/unittest_templates/model_crud_update_all_fields.jinja
djangoaddicts/codegen/management/commands/unittest_templates/viewset.jinja
djangoaddicts/codegen/management/commands/unittest_templates/_viewset/viewset_action.jinja
djangoaddicts/codegen/management/commands/unittest_templates/_viewset/viewset_action_auth.jinja
djangoaddicts/codegen/management/commands/unittest_templates/_viewset/viewset_action_noauth.jinja
djangoaddicts/codegen/management/commands/unittest_templates/_viewset/viewset_detail.jinja
djangoaddicts/codegen/management/commands/unittest_templates/_viewset/viewset_detail_auth.jinja
djangoaddicts/codegen/management/commands/unittest_templates/_viewset/viewset_detail_noauth.jinja
djangoaddicts/codegen/management/commands/unittest_templates/_viewset/viewset_list.jinja
djangoaddicts/codegen/management/commands/unittest_templates/_viewset/viewset_list_auth.jinja
djangoaddicts/codegen/management/commands/unittest_templates/_viewset/viewset_list_noauth.jinja
djangoaddicts/codegen/management/commands/unittest_templates/viewset/base.jinja
djangoaddicts/codegen/management/commands/unittest_templates/viewset/create.jinja
djangoaddicts/codegen/management/commands/unittest_templates/viewset/destroy.jinja
djangoaddicts.codegen-0.0.0.dist-info/LICENSE
djangoaddicts.codegen-0.0.0.dist-info/METADATA
djangoaddicts.codegen-0.0.0.dist-info/WHEEL
djangoaddicts.codegen-0.0.0.dist-info/top_level.txt
djangoaddicts.codegen-0.0.0.dist-info/zip-safe
djangoaddicts.codegen-0.0.0.dist-info/RECORD
